pyhttps.py
setup.cfg
setup.py
version.py
pyhttps.egg-info/PKG-INFO
pyhttps.egg-info/SOURCES.txt
pyhttps.egg-info/dependency_links.txt
pyhttps.egg-info/entry_points.txt
pyhttps.egg-info/top_level.txt