Metadata-Version: 1.0
Name: pyhttps
Version: 0.0.3
Summary: Simple python https server creator
Home-page: https://github.com/talhasch/pyhttps
Author: Talha Buğra Bulut
Author-email: talhabugrabulut@gmail.com
License: UNKNOWN
Keywords: https,server
Platform: UNKNOWN
